gempaterkini/__init__.py
latestearthquake_nusantara-0.2.dist-info/LICENSE
latestearthquake_nusantara-0.2.dist-info/METADATA
latestearthquake_nusantara-0.2.dist-info/WHEEL
latestearthquake_nusantara-0.2.dist-info/top_level.txt
latestearthquake_nusantara-0.2.dist-info/RECORD
