Metadata-Version: 2.1
Name: latestearthquake-nusantara
Version: 0.2
Summary: This package will get the latest earthquake from BMKG | Meteorogical, Climatological, and Geophysical Agency
Home-page: https://github.com/mohehsan/latest-earthquake
Author: Muhammad Ihsan
Author-email: muhammadihsan3011@gmail.com
License: UNKNOWN
Project-URL: Website, https://www.mohammed-ehsan.com/
Platform: UNKNOWN
Classifier: Programming Language :: Python :: 3
Classifier: License :: OSI Approved :: GNU General Public License v3 (GPLv3)
Classifier: Operating System :: OS Independent
Requires-Python: >=3.6
License-File: LICENSE
